libjam/__init__.py
libjam/captain.py
libjam/clipboard.py
libjam/cloud.py
libjam/drawer.py
libjam/extract_functions.py
libjam/flashcard.py
libjam/notebook.py
libjam/typewriter.py
libjam-0.1.9.dist-info/METADATA
libjam-0.1.9.dist-info/WHEEL
libjam-0.1.9.dist-info/licenses/LICENSE
libjam-0.1.9.dist-info/RECORD
