Metadata-Version: 2.4
Name: libjam
Version: 0.1.9
Summary: A library jam for Python.
Project-URL: Homepage, https://github.com/philippkosarev/libjam
Project-URL: Issues, https://github.com/philippkosarev/libjam/issues
Author-email: Philipp Kosarev <philipp.kosarev@gmail.com>
License-Expression: GPL-2.0
License-File: LICENSE
Classifier: Operating System :: OS Independent
Classifier: Programming Language :: Python :: 3
Requires-Python: >=3.14.0
Requires-Dist: filetype>=1.0.0
Requires-Dist: platformdirs>=4.0.0
Requires-Dist: py7zr>=1.0.0
Requires-Dist: rarfile>=4.0
Requires-Dist: requests>=2.0.0
Requires-Dist: send2trash>=1.8.0
Requires-Dist: toml>=0.10.0
